comtool_plugin_myplugin2/__init__.py
comtool_plugin_myplugin2/myplugin2.py
comtool_plugin_myplugin2/plugin_i18n.py
comtool_plugin_myplugin2-1.0.0.data/data/README.MD
comtool_plugin_myplugin2-1.0.0.dist-info/METADATA
comtool_plugin_myplugin2-1.0.0.dist-info/WHEEL
comtool_plugin_myplugin2-1.0.0.dist-info/top_level.txt
comtool_plugin_myplugin2-1.0.0.dist-info/RECORD
