Metadata-Version: 2.1
Name: comtool-plugin-myplugin2
Version: 1.0.0
Summary: plugin demo for comtool
Home-page: https://github.com/Neutree/COMTool
Author: Neucrack
Author-email: czd666666@gmail.com
License: LGPL-3.0
Keywords: comtool plugin
Platform: UNKNOWN
Classifier: Development Status :: 5 - Production/Stable
Classifier: Intended Audience :: Developers
Classifier: Topic :: Software Development :: Embedded Systems
Classifier: Topic :: Software Development :: Debuggers
Classifier: License :: OSI Approved :: GNU Lesser General Public License v3 (LGPLv3)
Classifier: Programming Language :: Python :: 3
Classifier: Programming Language :: Python :: 3.8
Classifier: Programming Language :: Python :: 3.9
Classifier: Programming Language :: Python :: 3.10
